alignak_backend/__init__.py
alignak_backend/app.py
alignak_backend/carboniface.py
alignak_backend/grafana.py
alignak_backend/livesynthesis.py
alignak_backend/main.py
alignak_backend/perfdata.py
alignak_backend/scheduler.py
alignak_backend/template.py
alignak_backend/timeseries.py
alignak_backend/models/__init__.py
alignak_backend/models/actionacknowledge.py
alignak_backend/models/actiondowntime.py
alignak_backend/models/actionforcecheck.py
alignak_backend/models/alignak.py
alignak_backend/models/alignak_notifications.py
alignak_backend/models/alignakdaemon.py
alignak_backend/models/alignakretention.py
alignak_backend/models/command.py
alignak_backend/models/grafana.py
alignak_backend/models/graphite.py
alignak_backend/models/history.py
alignak_backend/models/host.py
alignak_backend/models/hostdependency.py
alignak_backend/models/hostescalation.py
alignak_backend/models/hostgroup.py
alignak_backend/models/influxdb.py
alignak_backend/models/livesynthesis.py
alignak_backend/models/livesynthesisretention.py
alignak_backend/models/logcheckresult.py
alignak_backend/models/realm.py
alignak_backend/models/service.py
alignak_backend/models/servicedependency.py
alignak_backend/models/serviceescalation.py
alignak_backend/models/servicegroup.py
alignak_backend/models/statsd.py
alignak_backend/models/timeperiod.py
alignak_backend/models/timeseriesretention.py
alignak_backend/models/user.py
alignak_backend/models/usergroup.py
alignak_backend/models/userrestrictrole.py
alignak_backend/swagger-ui/__init__.py
alignak_backend/swagger-ui/index.html
alignak_backend/swagger-ui/o2c.html
alignak_backend/swagger-ui/swagger-ui.js
alignak_backend/swagger-ui/swagger-ui.min.js
alignak_backend/swagger-ui/css/print.css
alignak_backend/swagger-ui/css/reset.css
alignak_backend/swagger-ui/css/screen.css
alignak_backend/swagger-ui/css/style.css
alignak_backend/swagger-ui/css/typography.css
alignak_backend/swagger-ui/fonts/DroidSans-Bold.ttf
alignak_backend-1.4.16.dist-info/METADATA
alignak_backend-1.4.16.dist-info/RECORD
alignak_backend-1.4.16.dist-info/WHEEL
alignak_backend-1.4.16.dist-info/dependency_links.txt
alignak_backend-1.4.16.dist-info/entry_points.txt
alignak_backend-1.4.16.dist-info/top_level.txt
