Metadata-Version: 2.1
Name: alignak-backend
Version: 1.4.16
Summary: Alignak REST backend
Requires-Dist: future
Requires-Dist: docopt
Requires-Dist: jsonschema (==2.6.0)
Requires-Dist: jsmin (==2.2.2)
Requires-Dist: configparser (==3.5.0)
Requires-Dist: influxdb (==5.1.0)
Requires-Dist: statsd (==3.2.2)
Requires-Dist: Eve (==0.7.9)
Requires-Dist: Eve-Swagger (==0.0.11)
Requires-Dist: Flask (<=0.12,>=0.10.1)
Requires-Dist: Flask-Pymongo (<2.0.0)
Requires-Dist: flask-bootstrap (==3.3.7.1)
Requires-Dist: flask-apscheduler (==1.8.0)
